README.md
setup.py
dask_k8/__init__.py
dask_k8/cluster.py
dask_k8/default_configs.py
dask_k8.egg-info/PKG-INFO
dask_k8.egg-info/SOURCES.txt
dask_k8.egg-info/dependency_links.txt
dask_k8.egg-info/requires.txt
dask_k8.egg-info/top_level.txt