Metadata-Version: 2.1
Name: dask-k8
Version: 0.1.1
Summary: Simple library to start a Dask cluster on Kubernetes
Home-page: https://github.com/impresso/dask_k8
Author: Benoit Seguin
License: GPL
Platform: UNKNOWN
Classifier: Programming Language :: Python :: 3
Classifier: Programming Language :: Python :: 3.6
Classifier: Programming Language :: Python :: 3.7
Classifier: Programming Language :: Python :: 3.8
Requires-Python: >=3.6
